{"type":"PR","pr":{"number":31,"head":"ac6b281d57a1dc867ddcc37c8c2603bf30dc0408"},"user":"davedabuilder","status":"draft","branch":"cms/09-orthese-sportif","collection":"articlesfr","title":"Est-ce que une othèse plantaire peut être portée dans un patin? - Cryos Technologies","description":"La question est souvent posée par les sportifs sur patins; apprenez quels bénéfices procure le port d'orthèses plantaires dans vos patins.","objects":{"entry":{"path":"content/articles/09-orthese-sportif.md","sha":"0ad1f5920b59679249a884224dd4c74bc0d6ae7c"},"files":[]},"timeStamp":"2017-07-10T16:35:12.256Z"}